<annotation>
	<folder>VOC2007</folder>
	<filename>2014-11-07121751.jpg</filename>
	<source>
		<database>The VOC2007 Database</database>
		<annotation>PASCAL VOC2007</annotation>
		<image>flickr</image>
		<flickrid>NULL</flickrid>
	</source>
	<owner>
		<flickrid>NULL</flickrid>
		<name>WH</name>
	</owner>
	<size>
		<width>1600</width>
		<height>1200</height>
		<depth>3</depth>
	</size>
		<segmented>0</segmented>
	<object>
		<name>Vehicles</name>
		<pose>Unspecified</pose>
		<truncated>1</truncated>
		<difficult>0</difficult>
		<bndbox>
			<xmin>-115</xmin>
			<ymin>490</ymin>
			<xmax>115</xmax>
			<ymax>809</ymax>
		</bndbox>
	</object>
	<object>
		<name>Vehicles</name>
		<pose>Unspecified</pose>
		<truncated>1</truncated>
		<difficult>0</difficult>
		<bndbox>
			<xmin>-46</xmin>
			<ymin>622</ymin>
			<xmax>141</xmax>
			<ymax>726</ymax>
		</bndbox>
	</object>
	<object>
		<name>Vehicles</name>
		<pose>Unspecified</pose>
		<truncated>1</truncated>
		<difficult>0</difficult>
		<bndbox>
			<xmin>128</xmin>
			<ymin>625</ymin>
			<xmax>284</xmax>
			<ymax>723</ymax>
		</bndbox>
	</object>
	<object>
		<name>Vehicles</name>
		<pose>Unspecified</pose>
		<truncated>1</truncated>
		<difficult>0</difficult>
		<bndbox>
			<xmin>476</xmin>
			<ymin>654</ymin>
			<xmax>543</xmax>
			<ymax>701</ymax>
		</bndbox>
	</object>
	<object>
		<name>Vehicles</name>
		<pose>Unspecified</pose>
		<truncated>1</truncated>
		<difficult>0</difficult>
		<bndbox>
			<xmin>1330</xmin>
			<ymin>497</ymin>
			<xmax>1509</xmax>
			<ymax>703</ymax>
		</bndbox>
	</object>
	<object>
		<name>Vehicles</name>
		<pose>Unspecified</pose>
		<truncated>1</truncated>
		<difficult>0</difficult>
		<bndbox>
			<xmin>1046</xmin>
			<ymin>600</ymin>
			<xmax>1296</xmax>
			<ymax>731</ymax>
		</bndbox>
	</object>
	<object>
		<name>Vehicles</name>
		<pose>Unspecified</pose>
		<truncated>1</truncated>
		<difficult>0</difficult>
		<bndbox>
			<xmin>1023</xmin>
			<ymin>592</ymin>
			<xmax>1188</xmax>
			<ymax>707</ymax>
		</bndbox>
	</object>
	<object>
		<name>Vehicles</name>
		<pose>Unspecified</pose>
		<truncated>1</truncated>
		<difficult>0</difficult>
		<bndbox>
			<xmin>970</xmin>
			<ymin>644</ymin>
			<xmax>1085</xmax>
			<ymax>713</ymax>
		</bndbox>
	</object>
	<object>
		<name>Vehicles</name>
		<pose>Unspecified</pose>
		<truncated>1</truncated>
		<difficult>0</difficult>
		<bndbox>
			<xmin>887</xmin>
			<ymin>644</ymin>
			<xmax>963</xmax>
			<ymax>699</ymax>
		</bndbox>
	</object>
	<object>
		<name>Vehicles</name>
		<pose>Unspecified</pose>
		<truncated>1</truncated>
		<difficult>0</difficult>
		<bndbox>
			<xmin>578</xmin>
			<ymin>671</ymin>
			<xmax>636</xmax>
			<ymax>702</ymax>
		</bndbox>
	</object>
</annotation>