<annotation>
	<folder>VOC2007</folder>
	<filename>2015-11-28115540.jpg</filename>
	<source>
		<database>The VOC2007 Database</database>
		<annotation>PASCAL VOC2007</annotation>
		<image>flickr</image>
		<flickrid>NULL</flickrid>
	</source>
	<owner>
		<flickrid>NULL</flickrid>
		<name>WH</name>
	</owner>
	<size>
		<width>2592</width>
		<height>1944</height>
		<depth>3</depth>
	</size>
		<segmented>0</segmented>
	<object>
		<name>Vehicles</name>
		<pose>Unspecified</pose>
		<truncated>1</truncated>
		<difficult>0</difficult>
		<bndbox>
			<xmin>-358</xmin>
			<ymin>531</ymin>
			<xmax>603</xmax>
			<ymax>899</ymax>
		</bndbox>
	</object>
	<object>
		<name>Vehicles</name>
		<pose>Unspecified</pose>
		<truncated>1</truncated>
		<difficult>0</difficult>
		<bndbox>
			<xmin>1437</xmin>
			<ymin>798</ymin>
			<xmax>1520</xmax>
			<ymax>862</ymax>
		</bndbox>
	</object>
	<object>
		<name>Vehicles</name>
		<pose>Unspecified</pose>
		<truncated>1</truncated>
		<difficult>0</difficult>
		<bndbox>
			<xmin>1529</xmin>
			<ymin>781</ymin>
			<xmax>1598</xmax>
			<ymax>854</ymax>
		</bndbox>
	</object>
	<object>
		<name>Vehicles</name>
		<pose>Unspecified</pose>
		<truncated>1</truncated>
		<difficult>0</difficult>
		<bndbox>
			<xmin>1607</xmin>
			<ymin>740</ymin>
			<xmax>1772</xmax>
			<ymax>877</ymax>
		</bndbox>
	</object>
	<object>
		<name>Vehicles</name>
		<pose>Unspecified</pose>
		<truncated>1</truncated>
		<difficult>0</difficult>
		<bndbox>
			<xmin>1636</xmin>
			<ymin>729</ymin>
			<xmax>1845</xmax>
			<ymax>887</ymax>
		</bndbox>
	</object>
	<object>
		<name>Vehicles</name>
		<pose>Unspecified</pose>
		<truncated>1</truncated>
		<difficult>0</difficult>
		<bndbox>
			<xmin>1977</xmin>
			<ymin>190</ymin>
			<xmax>2386</xmax>
			<ymax>994</ymax>
		</bndbox>
	</object>
	<object>
		<name>Vehicles</name>
		<pose>Unspecified</pose>
		<truncated>1</truncated>
		<difficult>0</difficult>
		<bndbox>
			<xmin>1853</xmin>
			<ymin>766</ymin>
			<xmax>2049</xmax>
			<ymax>870</ymax>
		</bndbox>
	</object>
</annotation>