<annotation>
	<folder>VOC2007</folder>
	<filename>2015-04-01152452.jpg</filename>
	<source>
		<database>The VOC2007 Database</database>
		<annotation>PASCAL VOC2007</annotation>
		<image>flickr</image>
		<flickrid>NULL</flickrid>
	</source>
	<owner>
		<flickrid>NULL</flickrid>
		<name>WH</name>
	</owner>
	<size>
		<width>1600</width>
		<height>1200</height>
		<depth>3</depth>
	</size>
		<segmented>0</segmented>
	<object>
		<name>Vehicles</name>
		<pose>Unspecified</pose>
		<truncated>1</truncated>
		<difficult>0</difficult>
		<bndbox>
			<xmin>867</xmin>
			<ymin>508</ymin>
			<xmax>1059</xmax>
			<ymax>605</ymax>
		</bndbox>
	</object>
	<object>
		<name>Vehicles</name>
		<pose>Unspecified</pose>
		<truncated>1</truncated>
		<difficult>0</difficult>
		<bndbox>
			<xmin>836</xmin>
			<ymin>579</ymin>
			<xmax>872</xmax>
			<ymax>606</ymax>
		</bndbox>
	</object>
	<object>
		<name>Vehicles</name>
		<pose>Unspecified</pose>
		<truncated>1</truncated>
		<difficult>0</difficult>
		<bndbox>
			<xmin>806</xmin>
			<ymin>568</ymin>
			<xmax>846</xmax>
			<ymax>607</ymax>
		</bndbox>
	</object>
	<object>
		<name>Vehicles</name>
		<pose>Unspecified</pose>
		<truncated>1</truncated>
		<difficult>0</difficult>
		<bndbox>
			<xmin>760</xmin>
			<ymin>522</ymin>
			<xmax>816</xmax>
			<ymax>586</ymax>
		</bndbox>
	</object>
	<object>
		<name>Vehicles</name>
		<pose>Unspecified</pose>
		<truncated>1</truncated>
		<difficult>0</difficult>
		<bndbox>
			<xmin>420</xmin>
			<ymin>557</ymin>
			<xmax>576</xmax>
			<ymax>611</ymax>
		</bndbox>
	</object>
</annotation>